epub_image_helper/__init__.py
epub_image_helper/cmd.py
epub_image_helper/common.py
epub_image_helper/epubImageHelper.py
epub_image_helper/testImageCompression.py
epub_image_helper/testPdf2Epub.py
epub_image_helper-1.0.7.dist-info/licenses/LICENSE
epub_image_helper-1.0.7.dist-info/METADATA
epub_image_helper-1.0.7.dist-info/WHEEL
epub_image_helper-1.0.7.dist-info/entry_points.txt
epub_image_helper-1.0.7.dist-info/top_level.txt
epub_image_helper-1.0.7.dist-info/RECORD
