Metadata-Version: 2.4
Name: epub-image-helper
Version: 1.0.7
Summary: This tool allows you to easily convert specified photos and images into EPUB e-book format, making it accessible for family and friends. It can be used to create monthly or yearly photo collections for children and transform travel photos into e-books.
Home-page: https://github.com/changyy/epub-image-helper
Download-URL: https://pypi.org/project/epub-image-helper/
Author: Yuan-Yi Chang
Author-email: <changyy.csie@gmail.com>
Keywords: python,epub,image,photo,album,pdf
Classifier: Programming Language :: Python :: 3
Classifier: Operating System :: MacOS :: MacOS X
Requires-Python: >=3.10
License-File: LICENSE
Requires-Dist: pandas
Dynamic: author
Dynamic: author-email
Dynamic: classifier
Dynamic: description
Dynamic: description-content-type
Dynamic: download-url
Dynamic: home-page
Dynamic: keywords
Dynamic: license-file
Dynamic: requires-dist
Dynamic: requires-python
Dynamic: summary
